LICENSE
MANIFEST.in
README.rst
rancidcmd.py
requirements.txt
setup.cfg
setup.py
docs/build/html/.buildinfo
docs/build/html/genindex.html
docs/build/html/index.html
docs/build/html/objects.inv
docs/build/html/py-modindex.html
docs/build/html/search.html
docs/build/html/searchindex.js
docs/htmlcov/coverage_html.js
docs/htmlcov/index.html
docs/htmlcov/jquery.debounce.min.js
docs/htmlcov/jquery.hotkeys.js
docs/htmlcov/jquery.isonscreen.js
docs/htmlcov/jquery.min.js
docs/htmlcov/jquery.tablesorter.min.js
docs/htmlcov/keybd_closed.png
docs/htmlcov/keybd_open.png
docs/htmlcov/rancidcmd.html
docs/htmlcov/rancidcmd_py.html
docs/htmlcov/status.dat
docs/htmlcov/status.json
docs/htmlcov/style.css
docs/source/index.rst
rancidcmd.egg-info/PKG-INFO
rancidcmd.egg-info/SOURCES.txt
rancidcmd.egg-info/dependency_links.txt
rancidcmd.egg-info/top_level.txt
tests/__init__.py
tests/test_rancidcmd.py